upordown_counter/upordown_counter.v
module upordown_counter (
    clk,reset,upordown,count
);
    
    input clk,reset,upordown;
    output [3:0]count;
    reg [3:0]count = 0;

    always @(posedge(clk) or posedge(count)) begin
        if (reset == 1)
            count <= 0;
        else if(upordown == 1)
            if(count == 15)
                count <= 0;
            else 
                count = count + 1;
        else 
            if(count == 0)
                count <= 15;
            else
            count = count - 1;
    end

    initial begin
        $dumpfile ("upordown_counter.vcd");
        $dumpvars (0, upordown_counter);
        #1;
    end

endmodule

upordown_counter/upordown_counter_tb.v
`include "upordown_counter.v"

module upordown_counter_tb ();

    reg clk,reset,upordown;
    wire [3:0]count;

    upordown_counter uut(clk,reset,upordown,count);

    initial clk = 0;
    always #5 clk = ~clk;

    initial begin
        reset = 0;
        upordown = 0;
        #300;
        upordown = 1;
        #300;      
        reset = 1;
        upordown = 1;
        #100;
        reset=0;
        $finish;
    end

endmodule

upordown_counter/upordown_counter.vcd
$date
	Tue Nov 21 00:40:55 2023
$end
$version
	Icarus Verilog
$end
$timescale
	1s
$end
$scope module upordown_counter_tb $end
$scope module uut $end
$var wire 1 ! clk $end
$var wire 1 " reset $end
$var wire 1 # upordown $end
$var reg 4 $ count [3:0] $end
$upscope $end
$upscope $end
$enddefinitions $end
$comment Show the parameter values. $end
$dumpall
$end
#0
$dumpvars
b0 $
0#
0"
0!
$end
#5
b1110 $
1!
#10
0!
#15
b1101 $
1!
#20
0!
#25
b1100 $
1!
#30
0!
#35
b1011 $
1!
#40
0!
#45
b1010 $
1!
#50
0!
#55
b1001 $
1!
#60
0!
#65
b1000 $
1!
#70
0!
#75
b111 $
1!
#80
0!
#85
b110 $
1!
#90
0!
#95
b101 $
1!
#100
0!
#105
b100 $
1!
#110
0!
#115
b11 $
1!
#120
0!
#125
b10 $
1!
#130
0!
#135
b1 $
1!
#140
0!
#145
b0 $
1!
#150
0!
#155
b1110 $
1!
#160
0!
#165
b1101 $
1!
#170
0!
#175
b1100 $
1!
#180
0!
#185
b1011 $
1!
#190
0!
#195
b1010 $
1!
#200
0!
#205
b1001 $
1!
#210
0!
#215
b1000 $
1!
#220
0!
#225
b111 $
1!
#230
0!
#235
b110 $
1!
#240
0!
#245
b101 $
1!
#250
0!
#255
b100 $
1!
#260
0!
#265
b11 $
1!
#270
0!
#275
b10 $
1!
#280
0!
#285
b1 $
1!
#290
0!
#295
b0 $
1!
#300
0!
1#
#305
b1 $
1!
#310
0!
#315
b10 $
1!
#320
0!
#325
b11 $
1!
#330
0!
#335
b100 $
1!
#340
0!
#345
b101 $
1!
#350
0!
#355
b110 $
1!
#360
0!
#365
b111 $
1!
#370
0!
#375
b1000 $
1!
#380
0!
#385
b1001 $
1!
#390
0!
#395
b1010 $
1!
#400
0!
#405
b1011 $
1!
#410
0!
#415
b1100 $
1!
#420
0!
#425
b1101 $
1!
#430
0!
#435
b1110 $
1!
#440
0!
#445
b1111 $
1!
#450
0!
#455
b0 $
1!
#460
0!
#465
b1 $
1!
#470
0!
#475
b10 $
1!
#480
0!
#485
b11 $
1!
#490
0!
#495
b100 $
1!
#500
0!
#505
b101 $
1!
#510
0!
#515
b110 $
1!
#520
0!
#525
b111 $
1!
#530
0!
#535
b1000 $
1!
#540
0!
#545
b1001 $
1!
#550
0!
#555
b1010 $
1!
#560
0!
#565
b1011 $
1!
#570
0!
#575
b1100 $
1!
#580
0!
#585
b1101 $
1!
#590
0!
#595
b1110 $
1!
#600
0!
1"
#605
b0 $
1!
#610
0!
#615
1!
#620
0!
#625
1!
#630
0!
#635
1!
#640
0!
#645
1!
#650
0!
#655
1!
#660
0!
#665
1!
#670
0!
#675
1!
#680
0!
#685
1!
#690
0!
#695
1!
#700
0!
0"
