priority_encoder/priority_encoder.v
module priority_encoder (
    input en, output [2:0]i, input [7:0]u
);

    assign i[2] = u[4] | u[5] | u[6] | u[7] & en;
    assign i[1] = u[2] | u[3] | u[6] | u[7] & en;
    assign i[0] = u[1] | u[3] | u[5] | u[7] & en;

    initial begin
        $dumpfile ("priority_encoder.vcd");
        $dumpvars (0, priority_encoder);
        #1;
    end
endmodule

priority_encoder/priority_encoder_tb.v
`include "priority_encoder.v"

module priority_encoder_tb ();
    reg en;
    wire [2:0]i;
    reg [7:0]u;

    priority_encoder uut(en,i,u);

    initial begin
        $monitor("en=%b i=%b u=%b", en,i,u);
        en = 1; u = 128; #5;
        en = 1; u = 64; #5;
        en = 1; u = 32; #5;
        en = 1; u = 16; #5;
        en = 1; u = 8; #5;
        en = 1; u = 4; #5;
        en = 1; u = 2; #5;
        en = 1; u = 1; #5;
        en = 0; u = 8'bx; #5;
        $finish;
    end

    
endmodule

priority_encoder/priority_encoder.vcd
$date
	Tue Nov 21 00:20:03 2023
$end
$version
	Icarus Verilog
$end
$timescale
	1s
$end
$scope module priority_encoder_tb $end
$scope module uut $end
$var wire 1 ! en $end
$var wire 8 " u [7:0] $end
$var wire 3 # i [2:0] $end
$upscope $end
$upscope $end
$enddefinitions $end
$comment Show the parameter values. $end
$dumpall
$end
#0
$dumpvars
b111 #
b10000000 "
1!
$end
#5
b110 #
b1000000 "
#10
b101 #
b100000 "
#15
b100 #
b10000 "
#20
b11 #
b1000 "
#25
b10 #
b100 "
#30
b1 #
b10 "
#35
b0 #
b1 "
#40
bx #
bx "
0!
