full_adder/full_adder_data.v
module full_adder_data (
    a,b,c,sum,cout
);

    input a,b,c;
    output sum,cout;

    assign sum = (a^b^c);
    assign cout = (a&b)|(b&c)|(a&c);
    
    initial begin
        $dumpfile ("full_adder_data.vcd");
        $dumpvars (0, full_adder_data);
        #1;
    end
endmodule

full_adder/full_adder_struct.v
module full_adder_struct (
    a,b,c,sum,cout
);
    
    input a,b,c;
    output sum,cout;
    wire w1,w2,w3,w4,w5;

    xor x1(w1,a,b);
    xor x2(sum,w1,c);

    and a1(w2,a,b);
    and a2(w3,a,c);
    and a3(w4,b,c);

    or o1(w5,w2,w3);
    or o2(cout,w5,w4);

    initial begin
        $dumpfile ("full_adder_struct.vcd");
        $dumpvars (0, full_adder_struct);
        #1;
    end

endmodule

full_adder/full_adder_tb.v
// `include "full_adder_data.v"
`include "full_adder_struct.v"

module full_adder_tb ();

    reg a,b,c;
    wire sum,cout;

    // full_adder_data uut(a,b,c,sum,cout);
    full_adder_struct uut(a,b,c,sum,cout);

    initial begin
        a = 1'b0;
        b = 1'b0;
        c = 1'b0;
        #10;

        a = 1'b0;
        b = 1'b0;
        c = 1'b1;
        #10;

        a = 1'b0;
        b = 1'b1;
        c = 1'b0;
        #10;

        a = 1'b0;
        b = 1'b1;
        c = 1'b1;
        #10;

        a = 1'b1;
        b = 1'b0;
        c = 1'b0;
        #10;

        a = 1'b1;
        b = 1'b0;
        c = 1'b1;
        #10;

        a = 1'b1;
        b = 1'b1;
        c = 1'b0;
        #10;

        a = 1'b1;
        b = 1'b1;
        c = 1'b1;
        #10;

        $finish;
    end
    
endmodule

full_adder/full_adder_struct.vcd
$date
	Mon Nov 20 21:14:40 2023
$end
$version
	Icarus Verilog
$end
$timescale
	1s
$end
$scope module full_adder_tb $end
$scope module uut $end
$var wire 1 ! a $end
$var wire 1 " b $end
$var wire 1 # c $end
$var wire 1 $ cout $end
$var wire 1 % sum $end
$var wire 1 & w1 $end
$var wire 1 ' w2 $end
$var wire 1 ( w3 $end
$var wire 1 ) w4 $end
$var wire 1 * w5 $end
$upscope $end
$upscope $end
$enddefinitions $end
$comment Show the parameter values. $end
$dumpall
$end
#0
$dumpvars
0*
0)
0(
0'
0&
0%
0$
0#
0"
0!
$end
#10
1%
1#
#20
1&
0#
1"
#30
1$
0%
1)
1#
#40
0$
1%
0)
0#
0"
1!
#50
1$
1*
0%
1(
1#
#60
0(
0&
1'
0#
1"
#70
1%
1(
1)
1#
